<beans 
	xmlns="http://www.springframework.org/schema/beans" 
	xmlns:security="http://www.springframework.org/schema/security"
	xmlns:xsi="http://www.w3.org/2001/XMLSchema-instance"
	xsi:schemaLocation="http://www.springframework.org/schema/beans
	http://www.springframework.org/schema/beans/spring-beans-3.0.xsd
	http://www.springframework.org/schema/security
	http://www.springframework.org/schema/security/spring-security-3.1.xsd">
	
	<security:http pattern="/js/**" security="none" />
	<security:http pattern="/commons/**" security="none" />
	<security:http pattern="/media/**" security="none" />
	<security:http pattern="/403*" security="none" />
	<security:http pattern="/404*" security="none" />
	<security:http pattern="/500*" security="none" />
	<security:http pattern="/servlet/ValidCode" security="none"/>
	
	<security:http  entry-point-ref="multipleAuthenticationLoginEntry"  servlet-api-provision="true">
		
		<!--
		<security:session-management invalid-session-url="/loginRedirect.ht">
			<security:concurrency-control error-if-maximum-exceeded="false" max-sessions="1" expired-url="/loginRedirect.ht"/>
		</security:session-management>
		-->
		<!--使用表单登录-->
		<security:remember-me key="bpm3PrivateKey"/> 
		<security:logout logout-url="/logout" logout-success-url="/loginRedirect.ht"/> 
		<security:custom-filter  ref="aopFilter" after="FORM_LOGIN_FILTER" />
		
		<security:custom-filter  before="FILTER_SECURITY_INTERCEPTOR" ref="permissionFilter" />
		<security:access-denied-handler ref="htAccessDeniedHandler"/>
		<security:custom-filter position="SWITCH_USER_FILTER" ref="switchUserProcessingFilter"/>
		
	</security:http>
	
	<bean id="actionPageMap" class="java.util.HashMap">
		<constructor-arg>
			<map>
				<entry key="mobile" value="/mobileLogin.jsp"></entry>
			</map>
		</constructor-arg>
	</bean>
	
	<bean id="switchUserProcessingFilter" class="com.hotent.core.web.filter.HtSwitchUserFilter">
            <property name="userDetailsService" ref="sysUserDao" />
            <property name="switchUserUrl" value="/j_spring_security_switch_user" />
            <property name="exitUserUrl" value="/j_spring_security_exit_user" />
            <property name="targetUrl" value="/platform/console/main.ht" />
    </bean>

	
	<!--登录入口定义-->
	<bean id="multipleAuthenticationLoginEntry"    class="com.hotent.core.web.security.MultipleAuthenticationLoginEntry">  
        <property name="defaultLoginUrl" value="/login.jsp"/>  
        <property name="directUrlResolvers">  
            <list>  
                <ref bean="mobileLoginEntry"/>  
            </list>  
        </property>  
    </bean>  
  	
  	<!-- 跳转到手机登陆页 -->
    <bean id="mobileLoginEntry" class="com.hotent.core.web.security.RequestUriDirectUrlResolver">  
        <property name="pattern" value="/mobile"/>  
        <property name="directUrl" value="/mobileLogin.jsp"/>  
    </bean>  
  
	<bean id="htAccessDeniedHandler" class="com.hotent.core.web.security.HtAccessDeniedHandler">
		<property name="accessDeniedUrl" value="/commons/403.jsp"></property>
	</bean>
		
	<!-- 认证管理器，实现用户认证的入口，主要实现UserDetailsService接口即可 -->
	<security:authentication-manager alias="authenticationManager" >
		<security:authentication-provider user-service-ref="sysUserDao">
			<security:password-encoder hash="sha-256" base64="true"/>
		</security:authentication-provider>
	</security:authentication-manager>
	
	<bean id="aopFilter" class="com.hotent.core.web.filter.AopFilter"></bean>
	<!-- 一个自定义的filter，必须包含authenticationManager,accessDecisionManager,securityMetadataSource三个属性，我们的所有控制将在这三个类中实现 -->

	<bean id="permissionFilter" class="com.hotent.core.web.filter.PermissionFilter">
		<property name="authenticationManager" ref="authenticationManager" />
		<property name="accessDecisionManager" ref="accessDecisionManager" />
		<property name="securityMetadataSource" ref="securityMetadataSource" />
	</bean>

	<!-- 访问决策器，决定某个用户具有的角色，是否有足够的权限去访问某个资源 -->
	<bean id="accessDecisionManager" class="com.hotent.core.web.security.HtDecisionManager" />

	<!-- 资源源数据定义，即定义某一资源可以被哪些角色访问 -->
	<bean id="securityMetadataSource"
		class="com.hotent.core.web.security.HtSecurityMetadataSource" scope="singleton" >
		
		<property name="anonymousUrls">
			<set>
				<value>/mobileLogin.jsp</value>
				<value>/mobileLogin.ht</value>
				<value>/platform/mobile/lang/changLang.ht</value>
				<value>/loginRedirect.ht</value>
				<value>/login.jsp</value>
				<value>/login.ht</value>
				<value>/bpmImage</value>
				<value>/platform/bpm/processRun/processImage.ht</value>
				<value>/platform/bpm/processRun/getFlowStatusByInstanceId.ht</value>
				<value>/platform/bpm/processRun/taskUser.ht</value>
				<value>/platform/bpm/taskOpinion/list.ht</value>
				<!-- flex附件上传的 -->
				<value>/platform/bpm/bpmDefinition/getXmlImport.ht</value>
				<value>/mobile/system/mobileLogin.ht</value>
				<value>/mobile/system/mobileLogout.ht</value>
			</set>
		</property>
	</bean>
</beans>